opticomp/__init__.py
opticomp/_core/__init__.py
opticomp/_core/benchmark_suite.py
opticomp/_core/result_benchmark.py
opticomp/_core/result_wrapper.py
opticomp/_core/wrapper_interface.py
opticomp/objective_zoo/__init__.py
opticomp/objective_zoo/ackley_function.py
opticomp/objective_zoo/griewank_function.py
opticomp/objective_zoo/rosenbrock_function.py
opticomp/objective_zoo/sphere_function.py
opticomp/wrapper_zoo/__init__.py
opticomp/wrapper_zoo/bayes_opt/__init__.py
opticomp/wrapper_zoo/bayes_opt/wrapper_bayesian_optimization.py
opticomp/wrapper_zoo/optuna/__init__.py
opticomp/wrapper_zoo/optuna/wrapper_optuna_random.py
opticomp/wrapper_zoo/optuna/wrapper_optuna_tpe.py
OptiComp-0.2.0.dist-info/LICENSE
OptiComp-0.2.0.dist-info/METADATA
OptiComp-0.2.0.dist-info/WHEEL
OptiComp-0.2.0.dist-info/top_level.txt
OptiComp-0.2.0.dist-info/RECORD
